pytorch_ie/__init__.py
pytorch_ie/annotations.py
pytorch_ie/core/__init__.py
pytorch_ie/datamodule.py
pytorch_ie/dataset.py
pytorch_ie/documents.py
pytorch_ie/metrics/__init__.py
pytorch_ie/metrics/statistics/__init__.py
pytorch_ie/metrics/statistics/token_count_collector.py
pytorch_ie/model.py
pytorch_ie/models/__init__.py
pytorch_ie/models/base_models/__init__.py
pytorch_ie/models/base_models/bart_as_pointer_network.py
pytorch_ie/models/base_models/bart_with_decoder_position_ids.py
pytorch_ie/models/common/__init__.py
pytorch_ie/models/common/has_taskmodule.py
pytorch_ie/models/common/model_with_boilerplate.py
pytorch_ie/models/common/model_with_metrics_from_taskmodule.py
pytorch_ie/models/common/stages.py
pytorch_ie/models/components/__init__.py
pytorch_ie/models/components/pointer_head.py
pytorch_ie/models/components/pooler.py
pytorch_ie/models/components/seq2seq_encoder.py
pytorch_ie/models/genre/__init__.py
pytorch_ie/models/interface.py
pytorch_ie/models/modules/__init__.py
pytorch_ie/models/modules/mlp.py
pytorch_ie/models/sequence_classification_with_pooler.py
pytorch_ie/models/simple_generative.py
pytorch_ie/models/simple_sequence_classification.py
pytorch_ie/models/simple_token_classification.py
pytorch_ie/models/token_classification_with_seq2seq_encoder_and_crf.py
pytorch_ie/models/transformer_seq2seq.py
pytorch_ie/models/transformer_span_classification.py
pytorch_ie/models/transformer_text_classification.py
pytorch_ie/models/transformer_token_classification.py
pytorch_ie/pipeline.py
pytorch_ie/taskmodules/__init__.py
pytorch_ie/taskmodules/common/__init__.py
pytorch_ie/taskmodules/common/interfaces.py
pytorch_ie/taskmodules/common/mixins.py
pytorch_ie/taskmodules/common/taskmodule_with_document_converter.py
pytorch_ie/taskmodules/common/utils.py
pytorch_ie/taskmodules/cross_text_binary_coref.py
pytorch_ie/taskmodules/interface.py
pytorch_ie/taskmodules/labeled_span_extraction_by_token_classification.py
pytorch_ie/taskmodules/metrics/__init__.py
pytorch_ie-0.33.0.dist-info/METADATA
pytorch_ie-0.33.0.dist-info/WHEEL
pytorch_ie-0.33.0.dist-info/licenses/LICENSE
pytorch_ie-0.33.0.dist-info/RECORD
