Metadata-Version: 2.4
Name: pytorch-ie
Version: 0.33.0
Summary: State-of-the-art Information Extraction in PyTorch
License: MIT
License-File: LICENSE
Author: Arne Binder
Author-email: arne.b.binder@gmail.com
Requires-Python: >=3.10,<4.0
Classifier: Framework :: Pytest
Classifier: License :: OSI Approved :: MIT License
Classifier: Programming Language :: Python
Classifier: Programming Language :: Python :: 3
Classifier: Programming Language :: Python :: 3.10
Classifier: Programming Language :: Python :: 3.11
Classifier: Programming Language :: Python :: 3.12
Classifier: Programming Language :: Python :: 3.13
Classifier: Programming Language :: Python :: 3.14
Classifier: Programming Language :: Python :: 3 :: Only
Requires-Dist: pie-core (>=0.2.1,<0.4.0)
Requires-Dist: pie-documents (>=0.1.0,<0.2.0)
Requires-Dist: pytorch-lightning (>=2,<3)
Requires-Dist: torch (>=1.10)
Requires-Dist: torchmetrics[text] (>=1.5,<2)
Requires-Dist: transformers (>=4.35.0,<4.37.0)
Project-URL: Bug Tracker, https://github.com/arnebinder/pytorch-ie/issues
Project-URL: Changelog, https://github.com/arnebinder/pytorch-ie/releases
Project-URL: Documentation, https://pytorch-ie.readthedocs.io
Project-URL: Homepage, https://github.com/arnebinder/pytorch-ie
Project-URL: Repository, https://github.com/arnebinder/pytorch-ie
